<?xml version="1.0" encoding="utf-8" ?>
<dwsync>
<file name="bx_loader.gif" server="access941215561.webspace-data.io" local="133636404810000000" remote="133636404810000000" Dst="2" />
<file name="controls.png" server="access941215561.webspace-data.io" local="133636404830000000" remote="133636404830000000" Dst="2" />
<file name="hedder-bg.jpg" server="access941215561.webspace-data.io" local="133636404850000000" remote="133636404850000000" Dst="2" />
<file name="menu-2nd.jpg" server="access941215561.webspace-data.io" local="133636404900000000" remote="133636404900000000" Dst="2" />
<file name="logo.png" server="access941215561.webspace-data.io" local="133636404890000000" remote="133636404890000000" Dst="2" />
<file name="location.png" server="access941215561.webspace-data.io" local="133636404870000000" remote="133636404870000000" Dst="2" />
<file name="calender.png" server="access941215561.webspace-data.io" local="133636404810000000" remote="133636404810000000" Dst="2" />
<file name="time.png" server="access941215561.webspace-data.io" local="133636404950000000" remote="133636404950000000" Dst="2" />
<file name="members.png" server="access941215561.webspace-data.io" local="133636404890000000" remote="133636404890000000" Dst="2" />
<file name="lauage.png" server="access941215561.webspace-data.io" local="133636404870000000" remote="133636404870000000" Dst="2" />
<file name="bags.png" server="access941215561.webspace-data.io" local="133636404810000000" remote="133636404810000000" Dst="2" />
<file name="money.png" server="access941215561.webspace-data.io" local="133636404900000000" remote="133636404900000000" Dst="2" />
<file name="hedding-bg.png" server="access941215561.webspace-data.io" local="133636404850000000" remote="133636404850000000" Dst="2" />
<file name="hedding-bg1.png" server="access941215561.webspace-data.io" local="133636404860000000" remote="133636404860000000" Dst="2" />
<file name="cars-bg.jpg" server="access941215561.webspace-data.io" local="133636404820000000" remote="133636404820000000" Dst="2" />
<file name="bg-con.jpg" server="access941215561.webspace-data.io" local="133636404810000000" remote="133636404810000000" Dst="2" />
<file name="city.png" server="access941215561.webspace-data.io" local="133636404820000000" remote="133636404820000000" Dst="2" />
<file name="radio.png" server="access941215561.webspace-data.io" local="133636404940000000" remote="133636404940000000" Dst="2" />
<file name="line-2nd.png" server="access941215561.webspace-data.io" local="133636404870000000" remote="133636404870000000" Dst="2" />
<file name="cars1-2nd.png" server="access941215561.webspace-data.io" local="133636404820000000" remote="133636404820000000" Dst="2" />
<file name="arrow-2nd.png" server="access941215561.webspace-data.io" local="133636404810000000" remote="133636404810000000" Dst="2" />
<file name="cars-2nd.png" server="access941215561.webspace-data.io" local="133636404810000000" remote="133636404810000000" Dst="2" />
<file name="car-selex-icons-2nd.png" server="access941215561.webspace-data.io" local="133636404810000000" remote="133636404810000000" Dst="2" />
<file name="check.png" server="access941215561.webspace-data.io" local="133636404820000000" remote="133636404820000000" Dst="2" />
<file name="pass-bg.png" server="access941215561.webspace-data.io" local="133636404930000000" remote="133636404930000000" Dst="2" />
<file name="username.png" server="access941215561.webspace-data.io" local="133636404960000000" remote="133636404960000000" Dst="2" />
<file name="lock.png" server="access941215561.webspace-data.io" local="133636404870000000" remote="133636404870000000" Dst="2" />
<file name="user.png" server="access941215561.webspace-data.io" local="133636404960000000" remote="133636404960000000" Dst="2" />
<file name="phone.png" server="access941215561.webspace-data.io" local="133636404930000000" remote="133636404930000000" Dst="2" />
<file name="profile.png" server="access941215561.webspace-data.io" local="133636404940000000" remote="133636404940000000" Dst="2" />
<file name="overleybg.png" server="access941215561.webspace-data.io" local="133636404900000000" remote="133636404900000000" Dst="2" />
<file name="logo-re.png" server="access941215561.webspace-data.io" local="133636404890000000" remote="133636404890000000" Dst="2" />
<file name="waves3.svg" server="access941215561.webspace-data.io" local="133636404960000000" remote="133636404960000000" Dst="2" />
<file name="logo-2nd.png" server="access941215561.webspace-data.io" local="133636404890000000" remote="133636404890000000" Dst="2" />
<file name="route.png" server="access941215561.webspace-data.io" local="133636404940000000" remote="133636404940000000" Dst="2" />
<file name="id-card.png" server="access941215561.webspace-data.io" local="133636404860000000" remote="133636404860000000" Dst="2" />
<file name="credit-card.png" server="access941215561.webspace-data.io" local="133636404830000000" remote="133636404830000000" Dst="2" />
<file name="route1.png" server="access941215561.webspace-data.io" local="133636404940000000" remote="133636404940000000" Dst="2" />
<file name="id-card1.png" server="access941215561.webspace-data.io" local="133636404860000000" remote="133636404860000000" Dst="2" />
<file name="credit-card1.png" server="access941215561.webspace-data.io" local="133636404830000000" remote="133636404830000000" Dst="2" />
<file name="arrow.png" server="access941215561.webspace-data.io" local="133636404810000000" remote="133636404810000000" Dst="2" />
<file name="car-selex-icons.png" server="access941215561.webspace-data.io" local="133636404810000000" remote="133636404810000000" Dst="2" />
<file name="cars1.png" server="access941215561.webspace-data.io" local="133636404820000000" remote="133636404820000000" Dst="2" />
<file name="menu.jpg" server="access941215561.webspace-data.io" local="133636404900000000" remote="133636404900000000" Dst="2" />
<file name="line.png" server="access941215561.webspace-data.io" local="133636404870000000" remote="133636404870000000" Dst="2" />
<file name="cars.png" server="access941215561.webspace-data.io" local="133636404820000000" remote="133636404820000000" Dst="2" />
<file name="arrow-time.png" server="access941215561.webspace-data.io" local="133636404810000000" remote="133636404810000000" Dst="2" />
<file name="top_arr.png" server="access941215561.webspace-data.io" local="133636404950000000" remote="133636404950000000" Dst="2" />
<file name="sprite.png" server="access941215561.webspace-data.io" local="133636404940000000" remote="133636404940000000" Dst="2" />
<file name="anr.png" server="access941215561.webspace-data.io" local="133636404800000000" remote="133636404800000000" Dst="2" />
<file name="bg.png" server="access941215561.webspace-data.io" local="133636404810000000" remote="133636404810000000" Dst="2" />
<file name="car-img.jpg" server="access941215561.webspace-data.io" local="133636404810000000" remote="133636404810000000" Dst="2" />
<file name="cards1.gif" server="access941215561.webspace-data.io" local="133636404810000000" remote="133636404810000000" Dst="2" />
<file name="chosen-sprite.png" server="access941215561.webspace-data.io" local="133636404820000000" remote="133636404820000000" Dst="2" />
<file name="city1.jpg" server="access941215561.webspace-data.io" local="133636404820000000" remote="133636404820000000" Dst="2" />
<file name="city2.jpg" server="access941215561.webspace-data.io" local="133636404820000000" remote="133636404820000000" Dst="2" />
<file name="city3.jpg" server="access941215561.webspace-data.io" local="133636404820000000" remote="133636404820000000" Dst="2" />
<file name="city4.jpg" server="access941215561.webspace-data.io" local="133636404820000000" remote="133636404820000000" Dst="2" />
<file name="controls-2nd.png" server="access941215561.webspace-data.io" local="133636404820000000" remote="133636404820000000" Dst="2" />
<file name="controls-ye.png" server="access941215561.webspace-data.io" local="133636404820000000" remote="133636404820000000" Dst="2" />
<file name="cross.png" server="access941215561.webspace-data.io" local="133636404830000000" remote="133636404830000000" Dst="2" />
<file name="dummey.gif" server="access941215561.webspace-data.io" local="133636404830000000" remote="133636404830000000" Dst="2" />
<file name="hedding-bg.jpg" server="access941215561.webspace-data.io" local="133636404850000000" remote="133636404850000000" Dst="2" />
<file name="hedding-bg1.jpg" server="access941215561.webspace-data.io" local="133636404850000000" remote="133636404850000000" Dst="2" />
<file name="icons.png" server="access941215561.webspace-data.io" local="133636404860000000" remote="133636404860000000" Dst="2" />
<file name="img.jpg" server="access941215561.webspace-data.io" local="133636404860000000" remote="133636404860000000" Dst="2" />
<file name="index.html" server="access941215561.webspace-data.io" local="133636404860000000" remote="133636404860000000" Dst="2" />
<file name="ios.png" server="access941215561.webspace-data.io" local="133636404860000000" remote="133636404860000000" Dst="2" />
<file name="like.jpg" server="access941215561.webspace-data.io" local="133636404870000000" remote="133636404870000000" Dst="2" />
<file name="line-2nd.jpg" server="access941215561.webspace-data.io" local="133636404870000000" remote="133636404870000000" Dst="2" />
<file name="location-map.png" server="access941215561.webspace-data.io" local="133636404870000000" remote="133636404870000000" Dst="2" />
<file name="login-bg.jpg" server="access941215561.webspace-data.io" local="133636404890000000" remote="133636404890000000" Dst="2" />
<file name="mastercard.png" server="access941215561.webspace-data.io" local="133636404890000000" remote="133636404890000000" Dst="2" />
<file name="menu1.jpg" server="access941215561.webspace-data.io" local="133636404900000000" remote="133636404900000000" Dst="2" />
<file name="paypal-account.png" server="access941215561.webspace-data.io" local="133636404920000000" remote="133636404920000000" Dst="2" />
<file name="paypal.jpg" server="access941215561.webspace-data.io" local="133636404930000000" remote="133636404930000000" Dst="2" />
<file name="payumoney_logo.png" server="access941215561.webspace-data.io" local="133636404930000000" remote="133636404930000000" Dst="2" />
<file name="profile-img.jpg" server="access941215561.webspace-data.io" local="133636404930000000" remote="133636404930000000" Dst="2" />
<file name="rate.jpg" server="access941215561.webspace-data.io" local="133636404940000000" remote="133636404940000000" Dst="2" />
<file name="red-theme.jpg" server="access941215561.webspace-data.io" local="133636404940000000" remote="133636404940000000" Dst="2" />
<file name="sign-f.svg" server="access941215561.webspace-data.io" local="133636404940000000" remote="133636404940000000" Dst="2" />
<file name="sign-g.svg" server="access941215561.webspace-data.io" local="133636404940000000" remote="133636404940000000" Dst="2" />
<file name="Thumbs.db" server="access941215561.webspace-data.io" local="133636404950000000" remote="133636404950000000" Dst="2" />
<file name="top_arr-time.png" server="access941215561.webspace-data.io" local="133636404950000000" remote="133636404950000000" Dst="2" />
<file name="url.jpg" server="access941215561.webspace-data.io" local="133636404960000000" remote="133636404960000000" Dst="2" />
<file name="waves.svg" server="access941215561.webspace-data.io" local="133636404960000000" remote="133636404960000000" Dst="2" />
<file name="yellow-theme.jpg" server="access941215561.webspace-data.io" local="133636404960000000" remote="133636404960000000" Dst="2" />
</dwsync>